setup.py
first_distributions/Binomialdistribution.py
first_distributions/Gaussiandistribution.py
first_distributions/Generaldistribution.py
first_distributions/__init__.py
first_distributions.egg-info/PKG-INFO
first_distributions.egg-info/SOURCES.txt
first_distributions.egg-info/dependency_links.txt
first_distributions.egg-info/not-zip-safe
first_distributions.egg-info/top_level.txt